dbfpy3/__init__.py
dbfpy3/code_page.py
dbfpy3/dbf.py
dbfpy3/dbfpy3.py
dbfpy3/fields.py
dbfpy3/header.py
dbfpy3/memo.py
dbfpy3/record.py
dbfpy3/utils.py
dbfpy3-4.2.3.dist-info/licenses/LICENSE
dbfpy3-4.2.3.dist-info/METADATA
dbfpy3-4.2.3.dist-info/WHEEL
dbfpy3-4.2.3.dist-info/top_level.txt
dbfpy3-4.2.3.dist-info/RECORD
